pybasilica/__init__.py
pybasilica/main.py
pybasilica/run.py
pybasilica/simulation.py
pybasilica/svi.py
pybasilica/svi_mixture.py
pybasilica/utilities.py
pybasilica-0.4.0.dist-info/LICENSE
pybasilica-0.4.0.dist-info/METADATA
pybasilica-0.4.0.dist-info/WHEEL
pybasilica-0.4.0.dist-info/top_level.txt
pybasilica-0.4.0.dist-info/RECORD
